distcontrib_migrate
