Metadata-Version: 1.1
Name: distcontrib-migrate
Version: 0.1.1
Summary: Contributions to Distutils
Home-page: http://distcontrib-migrate.readthedocs.org/
Author: Richard Gomes http://rgomes-info.blogspot.com
Author-email: rgomes.info@gmail.com
License: OSI Approved :: BSD License
Keywords: distribute,setuptools,pip,sqlalchemy,migrate
Platform: UNKNOWN
Classifier: License :: OSI Approved :: BSD License
Classifier: Operating System :: OS Independent
Classifier: Programming Language :: Python
Classifier: Programming Language :: Cython
Classifier: Development Status :: 3 - Alpha
Classifier: Intended Audience :: Developers
Classifier: Environment :: Console
